dkd/__init__.py
dkd/ext/__init__.py
dkd/ext/msg.py
dkd/protocol/__init__.py
dkd/protocol/content.py
dkd/protocol/envelope.py
dkd/protocol/helpers.py
dkd/protocol/instant.py
dkd/protocol/message.py
dkd/protocol/reliable.py
dkd/protocol/secure.py
dkd-2.3.4.dist-info/LICENSE
dkd-2.3.4.dist-info/METADATA
dkd-2.3.4.dist-info/WHEEL
dkd-2.3.4.dist-info/top_level.txt
dkd-2.3.4.dist-info/RECORD
