Metadata-Version: 2.1
Name: dkd
Version: 2.3.4
Summary: A common message module
Home-page: https://github.com/dimchat/dkd-py
Author: Albert Moky
Author-email: albert.moky@gmail.com
License: MIT
Classifier: Programming Language :: Python :: 3
Classifier: License :: OSI Approved :: MIT License
Classifier: Operating System :: OS Independent
License-File: LICENSE
Requires-Dist: mkm (>=2.3.4)
